smc_lammps/__init__.py
smc_lammps/console.py
smc_lammps/run.py
smc_lammps/generate/__init__.py
smc_lammps/generate/default_parameters.py
smc_lammps/generate/generate.py
smc_lammps/generate/generator.py
smc_lammps/generate/parameters_template.py
smc_lammps/generate/seeds.csv
smc_lammps/generate/util.py
smc_lammps/generate/lammps/__init__.py
smc_lammps/generate/lammps/parameterfile.py
smc_lammps/generate/lammps/runtimes.py
smc_lammps/generate/lammps/util.py
smc_lammps/generate/structures/__init__.py
smc_lammps/generate/structures/polymer.py
smc_lammps/generate/structures/structure_creator.py
smc_lammps/generate/structures/dna/__init__.py
smc_lammps/generate/structures/dna/dna.py
smc_lammps/generate/structures/dna/dna_creator.py
smc_lammps/generate/structures/smc/__init__.py
smc_lammps/generate/structures/smc/smc.py
smc_lammps/generate/structures/smc/smc_creator.py
smc_lammps/lammps/cycle_adp.lmp
smc_lammps/lammps/cycle_apo.lmp
smc_lammps/lammps/cycle_disable.lmp
smc_lammps/lammps/equilibrate.lmp
smc_lammps/lammps/input.lmp
smc_lammps/post_process/__init__.py
smc_lammps/post_process/average_plot.py
smc_lammps/post_process/process_displacement.py
smc_lammps/post_process/smc_perspective.py
smc_lammps/post_process/types.py
smc_lammps/post_process/util.py
smc_lammps/post_process/visualize.py
smc_lammps/post_process/vmd.rc
smc_lammps/post_process/matplotlib/__init__.py
smc_lammps/post_process/matplotlib/draw.py
smc_lammps/reader/__init__.py
smc_lammps/reader/lammps_data.py
smc_lammps/reader/parser.py
smc_lammps/reader/util.py
smc_lammps/reader/tests/plane.py
smc_lammps-0.2.1.dist-info/METADATA
smc_lammps-0.2.1.dist-info/WHEEL
smc_lammps-0.2.1.dist-info/entry_points.txt
smc_lammps-0.2.1.dist-info/licenses/LICENSE
smc_lammps-0.2.1.dist-info/RECORD
