Metadata-Version: 2.4
Name: smc-lammps
Version: 0.2.1
Summary: Simulate DNA loop extrusion by SMCs using LAMMPS
Project-URL: Repository, https://github.com/LucasDooms/SMC_LAMMPS.git
Author: Stefanos Nomidis
Author-email: Lucas Dooms <lucas.dooms@kuleuven.be>
Maintainer-email: Lucas Dooms <lucas.dooms@kuleuven.be>
License-Expression: MIT
License-File: LICENSE
Keywords: DNA,LAMMPS,Molecular Dynamics,Structural Maintance of Chromosomes,coarse-grained,loop extrusion,simulation
Classifier: Programming Language :: Python :: 3 :: Only
Classifier: Programming Language :: Python :: 3.13
Requires-Python: >=3.13
Requires-Dist: argcomplete>=3.6.2
Requires-Dist: click>=8.2.1
Requires-Dist: matplotlib>=3.10.1
Requires-Dist: numpy>=2.2.4
Requires-Dist: rich>=14.0.0
Requires-Dist: scipy>=1.15.2
